snipit/__init__.py
snipit/api.py
snipit/command.py
snipit/scripts/__init__.py
snipit/scripts/snp_functions.py
snipit_mc-0.0.5.data/scripts/snp_functions.py
snipit_mc-0.0.5.dist-info/licenses/LICENSE
snipit_mc-0.0.5.dist-info/METADATA
snipit_mc-0.0.5.dist-info/WHEEL
snipit_mc-0.0.5.dist-info/entry_points.txt
snipit_mc-0.0.5.dist-info/top_level.txt
snipit_mc-0.0.5.dist-info/RECORD
