Metadata-Version: 2.4
Name: snipit-mc
Version: 0.0.5
Summary: Enhanced snipit with artistic color palettes and improved SNP visualization
Home-page: https://github.com/hyzhou1990/snipit-multicolor
Author: hyzhou1990
Author-email: 
License: GPL-3.0
Project-URL: Bug Reports, https://github.com/hyzhou1990/snipit-multicolor/issues
Project-URL: Source, https://github.com/hyzhou1990/snipit-multicolor
Project-URL: Documentation, https://github.com/hyzhou1990/snipit-multicolor#readme
Keywords: bioinformatics,snp,visualization,genomics,mutation,phylogenetics,sequence-analysis,covid,sars-cov-2,genbank
Classifier: Development Status :: 4 - Beta
Classifier: Intended Audience :: Science/Research
Classifier: License :: OSI Approved :: GNU General Public License v3 (GPLv3)
Classifier: Operating System :: OS Independent
Classifier: Programming Language :: Python :: 3
Classifier: Programming Language :: Python :: 3.7
Classifier: Programming Language :: Python :: 3.8
Classifier: Programming Language :: Python :: 3.9
Classifier: Programming Language :: Python :: 3.10
Classifier: Programming Language :: Python :: 3.11
Classifier: Topic :: Scientific/Engineering :: Bio-Informatics
Classifier: Topic :: Scientific/Engineering :: Visualization
Requires-Python: >=3.7
License-File: LICENSE
Requires-Dist: biopython>=1.70
Requires-Dist: matplotlib>=3.2.1
Dynamic: author
Dynamic: classifier
Dynamic: description
Dynamic: description-content-type
Dynamic: home-page
Dynamic: keywords
Dynamic: license
Dynamic: license-file
Dynamic: project-url
Dynamic: requires-dist
Dynamic: requires-python
Dynamic: summary
